MovementDetector/Watch.py
MovementDetector/__init__.py
tests/__init__.py
tests/test_watch.py
RaspberryPiMovementDetector-0.17.2.dist-info/LICENSE
RaspberryPiMovementDetector-0.17.2.dist-info/METADATA
RaspberryPiMovementDetector-0.17.2.dist-info/WHEEL
RaspberryPiMovementDetector-0.17.2.dist-info/top_level.txt
RaspberryPiMovementDetector-0.17.2.dist-info/RECORD
